README.md
setup.py
render_file_fullstackmqtt/__init__.py
render_file_fullstackmqtt/render_fullstackmqtt.py
render_file_fullstackmqtt.egg-info/PKG-INFO
render_file_fullstackmqtt.egg-info/SOURCES.txt
render_file_fullstackmqtt.egg-info/dependency_links.txt
render_file_fullstackmqtt.egg-info/top_level.txt