Metadata-Version: 2.1
Name: render-file-fullstackmqtt
Version: 0.0.2
Summary: render-file-fullstackmqtt supported for render html, css and js code.
Author: Phuc Bao
Author-email: nguyentranphucbao@gmail.com
